jupygrader/__about__.py
jupygrader/__init__.py
jupygrader/cli.py
jupygrader/constants.py
jupygrader/generate_assignment.py
jupygrader/grader.py
jupygrader/notebook_operations.py
jupygrader/obfuscate.py
jupygrader/types.py
jupygrader/utils.py
jupygrader/models/__init__.py
jupygrader/models/batch_grading_manager.py
jupygrader/models/grading_dataclasses.py
jupygrader/models/grading_task.py
jupygrader/resources/jupyter_cell_scripts/append_to_end_of_notebook.py
jupygrader/resources/jupyter_cell_scripts/grader_manual_template.py
jupygrader/resources/jupyter_cell_scripts/grader_template.py
jupygrader/resources/jupyter_cell_scripts/prepend_to_start_of_notebook.py
jupygrader-0.3.0.dist-info/METADATA
jupygrader-0.3.0.dist-info/WHEEL
jupygrader-0.3.0.dist-info/entry_points.txt
jupygrader-0.3.0.dist-info/licenses/LICENSE.txt
jupygrader-0.3.0.dist-info/RECORD
