Metadata-Version: 2.4
Name: jupygrader
Version: 0.3.0
Summary: Grade Jupyter notebooks with Python scripts
Project-URL: Documentation, https://github.com/subwaymatch/jupygrader#readme
Project-URL: Source, https://github.com/subwaymatch/jupygrader
Author-email: Ye Joo Park <subwaymatch@gmail.com>
License-Expression: MIT
License-File: LICENSE.txt
Keywords: autograder,autograding,grading,jupyter
Classifier: Development Status :: 4 - Beta
Classifier: Programming Language :: Python
Classifier: Programming Language :: Python :: 3.9
Classifier: Programming Language :: Python :: 3.10
Classifier: Programming Language :: Python :: 3.11
Classifier: Programming Language :: Python :: 3.12
Requires-Python: >=3.9
Requires-Dist: black
Requires-Dist: bs4
Requires-Dist: click
Requires-Dist: ipykernel
Requires-Dist: nbclient
Requires-Dist: nbconvert
Requires-Dist: nbformat
Requires-Dist: numpy
Requires-Dist: pandas
Requires-Dist: plotly
Requires-Dist: requests
Requires-Dist: statsmodels
Requires-Dist: tabulate
Requires-Dist: tqdm
Requires-Dist: tzlocal
Provides-Extra: docs
Requires-Dist: mkdocs-material; extra == 'docs'
Requires-Dist: mkdocstrings[python]; extra == 'docs'
